{"format":"csv","ignoreLeadingWhiteSpaceReading":null,"multiLine":null,"path":"dbfs:/databricks-datasets/bikeSharing/data-001/hour.csv","ignoreTrailingWhiteSpaceReading":null,"maxColumns":null,"writeMode":"error","description":"","separator":",","compression":null,"nullValue":null,"nanValue":null,"escapeQuotes":null,"charToEscapeQuoteEscaping":null,"encoding":null,"inferSchema":true,"enforceSchema":null,"quoteAll":null,"ignoreLeadingWhiteSpaceWriting":null,"locale":null,"quote":null,"timestampFormat":null,"emptyValue":null,"recursiveFileLookup":null,"partitionColumns":null,"schema":{"type":"struct","fields":[{"name":"instant","type":"integer","nullable":true,"metadata":{"description":"","mappings":[],"tags":[]}},{"name":"dteday","type":"date","nullable":true,"metadata":{"description":"","mappings":[],"tags":[]}},{"name":"season","type":"integer","nullable":true,"metadata":{"description":"","mappings":[],"tags":[]}},{"name":"yr","type":"integer","nullable":true,"metadata":{"description":"","mappings":[],"tags":[]}},{"name":"mnth","type":"integer","nullable":true,"metadata":{"description":"","mappings":[],"tags":[]}},{"name":"hr","type":"integer","nullable":true,"metadata":{"description":"","mappings":[],"tags":[]}},{"name":"holiday","type":"integer","nullable":true,"metadata":{"description":"","mappings":[],"tags":[]}},{"name":"weekday","type":"integer","nullable":true,"metadata":{"description":"","mappings":[],"tags":[]}},{"name":"workingday","type":"integer","nullable":true,"metadata":{"description":"","mappings":[],"tags":[]}},{"name":"weathersit","type":"integer","nullable":true,"metadata":{"description":"","mappings":[],"tags":[]}},{"name":"temp","type":"double","nullable":true,"metadata":{"description":"","mappings":[],"tags":[]}},{"name":"atemp","type":"double","nullable":true,"metadata":{"description":"","mappings":[],"tags":[]}},{"name":"hum","type":"double","nullable":true,"metadata":{"description":"","mappings":[],"tags":[]}},{"name":"windspeed","type":"double","nullable":true,"metadata":{"description":"","mappings":[],"tags":[]}},{"name":"casual","type":"integer","nullable":true,"metadata":{"description":"","mappings":[],"tags":[]}},{"name":"registered","type":"integer","nullable":true,"metadata":{"description":"","mappings":[],"tags":[]}},{"name":"cnt","type":"integer","nullable":true,"metadata":{"description":"","mappings":[],"tags":[]}}]},"escape":null,"unescapedQuoteHandling":null,"positiveInf":null,"comment":null,"lineSep":null,"componentInfo":{"gemId":"gitUri=http://gitserver:3000/DxEheDCJ_team_5751/DxEheDCJ_project_12654.git&subPath=&tag=0.2.5&projectSubscriptionProjectId=12654&path=gems/csv","projectName":"ProphecySparkBasicsPython"},"samplingRatio":null,"dateFormat":null,"mode":null,"header":true,"columnNameOfCorruptRecord":null,"modifiedBefore":null,"ignoreTrailingWhiteSpaceWriting":null,"maxCharsPerColumn":null,"negativeInf":null,"createSingleOutputFile":null,"pathGlobFilter":null,"datasetType":"File","useSchema":true,"modifiedAfter":null}